{"open toegang":{"appearances":0,"pages":[]},"open access":{"appearances":13,"pages":[48,48,57,114,114,114,114,114,115,115,115,115,115]},"open science":{"appearances":3,"pages":[48,53,57]},"open data":{"appearances":1,"pages":[71]},"open onderzoeksdata":{"appearances":0,"pages":[]},"onderzoeksdata":{"appearances":2,"pages":[49,53]},"datasets":{"appearances":1,"pages":[49]},"rdm":{"appearances":0,"pages":[]},"research data management":{"appearances":1,"pages":[49]},"fair":{"appearances":3,"pages":[27,49,102]},"dcc":{"appearances":2,"pages":[111,111]},"digital competence center":{"appearances":0,"pages":[]},"datasteward":{"appearances":0,"pages":[]},"data steward":{"appearances":0,"pages":[]},"dmp":{"appearances":0,"pages":[]},"data management plan":{"appearances":0,"pages":[]}}